{"title":"Кусь","id":"tg_name_Catkus","net.maunium.telegram.pack":null,"stickers":[{"body":"👋","url":"mxc://matrix.axelchat.ru/cnkspePaWSQgHtAsHBPGmqhi","info":{"w":512,"h":511,"size":23666,"mimetype":"image/webp","thumbnail_url":"mxc://matrix.axelchat.ru/gTsUPyrGQObmTBmtgbvLXPny","thumbnail_info":{"w":128,"h":128,"size":4308,"mimetype":"image/webp"}},"msgtype":"m.sticker","id":"mxc://matrix.axelchat.ru/cnkspePaWSQgHtAsHBPGmqhi","net.maunium.telegram.sticker":null},{"body":"😺","url":"mxc://matrix.axelchat.ru/suCKWOhizhnRrEuIQFZjxywz","info":{"w":512,"h":512,"size":17826,"mimetype":"image/webp","thumbnail_url":"mxc://matrix.axelchat.ru/BryXfToLpYkTlOCgkGnrUuJL","thumbnail_info":{"w":128,"h":128,"size":3282,"mimetype":"image/webp"}},"msgtype":"m.sticker","id":"mxc://matrix.axelchat.ru/suCKWOhizhnRrEuIQFZjxywz","net.maunium.telegram.sticker":null},{"body":"☺️","url":"mxc://matrix.axelchat.ru/dlNhzuLREfextGLFgzCAjQOJ","info":{"w":512,"h":511,"size":27634,"mimetype":"image/webp","thumbnail_url":"mxc://matrix.axelchat.ru/vFOVVomvcUtCSDcgyNzmxLQg","thumbnail_info":{"w":128,"h":128,"size":4958,"mimetype":"image/webp"}},"msgtype":"m.sticker","id":"mxc://matrix.axelchat.ru/dlNhzuLREfextGLFgzCAjQOJ","net.maunium.telegram.sticker":null},{"body":"😘","url":"mxc://matrix.axelchat.ru/OZzPYgwmqUrukAhZOwkPjQeg","info":{"w":512,"h":512,"size":19934,"mimetype":"image/webp","thumbnail_url":"mxc://matrix.axelchat.ru/eYzlONXQoaccNzNcxwrwsXFR","thumbnail_info":{"w":128,"h":128,"size":3818,"mimetype":"image/webp"}},"msgtype":"m.sticker","id":"mxc://matrix.axelchat.ru/OZzPYgwmqUrukAhZOwkPjQeg","net.maunium.telegram.sticker":null},{"body":"💋","url":"mxc://matrix.axelchat.ru/frsHjbUFoDnZRKmiwpPqPHDl","info":{"w":512,"h":512,"size":28664,"mimetype":"image/webp","thumbnail_url":"mxc://matrix.axelchat.ru/LKJziidOVaolNSwwgfpfAkwS","thumbnail_info":{"w":128,"h":128,"size":3504,"mimetype":"image/webp"}},"msgtype":"m.sticker","id":"mxc://matrix.axelchat.ru/frsHjbUFoDnZRKmiwpPqPHDl","net.maunium.telegram.sticker":null},{"body":"💑","url":"mxc://matrix.axelchat.ru/eSzkcuKmizdASqHgzDygXvma","info":{"w":512,"h":512,"size":22946,"mimetype":"image/webp","thumbnail_url":"mxc://matrix.axelchat.ru/NtNYgYBvFIlISeqcLmGwYpMw","thumbnail_info":{"w":128,"h":128,"size":4252,"mimetype":"image/webp"}},"msgtype":"m.sticker","id":"mxc://matrix.axelchat.ru/eSzkcuKmizdASqHgzDygXvma","net.maunium.telegram.sticker":null},{"body":"❄","url":"mxc://matrix.axelchat.ru/dCgYlNaOtdjEhNNUpkZsIolT","info":{"w":512,"h":512,"size":29498,"mimetype":"image/webp","thumbnail_url":"mxc://matrix.axelchat.ru/boXhCLCTFWJEbBbonfXETJPP","thumbnail_info":{"w":128,"h":128,"size":5004,"mimetype":"image/webp"}},"msgtype":"m.sticker","id":"mxc://matrix.axelchat.ru/dCgYlNaOtdjEhNNUpkZsIolT","net.maunium.telegram.sticker":null},{"body":"🤷","url":"mxc://matrix.axelchat.ru/EqkXoSCmxQzubPPkWsMEcRiD","info":{"w":512,"h":512,"size":33880,"mimetype":"image/webp","thumbnail_url":"mxc://matrix.axelchat.ru/PpGMwEkaDYYZDlSiQNJeNyyw","thumbnail_info":{"w":128,"h":128,"size":5408,"mimetype":"image/webp"}},"msgtype":"m.sticker","id":"mxc://matrix.axelchat.ru/EqkXoSCmxQzubPPkWsMEcRiD","net.maunium.telegram.sticker":null},{"body":"😤","url":"mxc://matrix.axelchat.ru/dYEFYIjhRNUaCXuJpSlAfSib","info":{"w":512,"h":512,"size":43656,"mimetype":"image/webp","thumbnail_url":"mxc://matrix.axelchat.ru/iWCMoRqrJAfzTMpyGrwIjcyf","thumbnail_info":{"w":128,"h":128,"size":5350,"mimetype":"image/webp"}},"msgtype":"m.sticker","id":"mxc://matrix.axelchat.ru/dYEFYIjhRNUaCXuJpSlAfSib","net.maunium.telegram.sticker":null},{"body":"😴","url":"mxc://matrix.axelchat.ru/ZbqAZZPViPHqAStFxLOBPZen","info":{"w":512,"h":512,"size":36074,"mimetype":"image/webp","thumbnail_url":"mxc://matrix.axelchat.ru/IBwSDgqYDDtFhrXWHlRZxURu","thumbnail_info":{"w":128,"h":128,"size":5454,"mimetype":"image/webp"}},"msgtype":"m.sticker","id":"mxc://matrix.axelchat.ru/ZbqAZZPViPHqAStFxLOBPZen","net.maunium.telegram.sticker":null},{"body":"😼","url":"mxc://matrix.axelchat.ru/bdRwuaZJRiOLEnOHchLhHbfQ","info":{"w":511,"h":512,"size":31900,"mimetype":"image/webp","thumbnail_url":"mxc://matrix.axelchat.ru/XlRqVdlhVdnJdvSkGCRBvolp","thumbnail_info":{"w":128,"h":128,"size":4748,"mimetype":"image/webp"}},"msgtype":"m.sticker","id":"mxc://matrix.axelchat.ru/bdRwuaZJRiOLEnOHchLhHbfQ","net.maunium.telegram.sticker":null},{"body":"💅","url":"mxc://matrix.axelchat.ru/QLmGWHUmLdvTkRFLjFvAJMVc","info":{"w":512,"h":511,"size":23490,"mimetype":"image/webp","thumbnail_url":"mxc://matrix.axelchat.ru/oJlpwaNUDtSAFoqXDsmwcldp","thumbnail_info":{"w":128,"h":128,"size":3952,"mimetype":"image/webp"}},"msgtype":"m.sticker","id":"mxc://matrix.axelchat.ru/QLmGWHUmLdvTkRFLjFvAJMVc","net.maunium.telegram.sticker":null},{"body":"😾","url":"mxc://matrix.axelchat.ru/sbkJzsGXNTfliSONtWRMbGnY","info":{"w":512,"h":511,"size":20986,"mimetype":"image/webp","thumbnail_url":"mxc://matrix.axelchat.ru/ABmKOEwMBkRmYAniiPzCSvlL","thumbnail_info":{"w":128,"h":128,"size":4242,"mimetype":"image/webp"}},"msgtype":"m.sticker","id":"mxc://matrix.axelchat.ru/sbkJzsGXNTfliSONtWRMbGnY","net.maunium.telegram.sticker":null},{"body":"😱","url":"mxc://matrix.axelchat.ru/wDuaqCPbebmAibqlUVAImDeA","info":{"w":511,"h":512,"size":22490,"mimetype":"image/webp","thumbnail_url":"mxc://matrix.axelchat.ru/CkDyyVUGnRdSaDrNGaMEQGhd","thumbnail_info":{"w":128,"h":128,"size":4340,"mimetype":"image/webp"}},"msgtype":"m.sticker","id":"mxc://matrix.axelchat.ru/wDuaqCPbebmAibqlUVAImDeA","net.maunium.telegram.sticker":null},{"body":"🎉","url":"mxc://matrix.axelchat.ru/QhPjElVXLMfgPrsvmrRmzpLT","info":{"w":512,"h":512,"size":22796,"mimetype":"image/webp","thumbnail_url":"mxc://matrix.axelchat.ru/bYeLeSIYwsYwqcMcRTvzGTMU","thumbnail_info":{"w":128,"h":128,"size":3976,"mimetype":"image/webp"}},"msgtype":"m.sticker","id":"mxc://matrix.axelchat.ru/QhPjElVXLMfgPrsvmrRmzpLT","net.maunium.telegram.sticker":null},{"body":"🍸","url":"mxc://matrix.axelchat.ru/kjfMkhjcHzxIJugjzpLTseUc","info":{"w":512,"h":512,"size":32456,"mimetype":"image/webp","thumbnail_url":"mxc://matrix.axelchat.ru/nDBoYfrdQxIGYGQGKYwPOuxC","thumbnail_info":{"w":128,"h":128,"size":4184,"mimetype":"image/webp"}},"msgtype":"m.sticker","id":"mxc://matrix.axelchat.ru/kjfMkhjcHzxIJugjzpLTseUc","net.maunium.telegram.sticker":null},{"body":"❤","url":"mxc://matrix.axelchat.ru/WopBhzaqHCdbhofutrxqMaNI","info":{"w":512,"h":512,"size":30084,"mimetype":"image/webp","thumbnail_url":"mxc://matrix.axelchat.ru/hjzZzwJLxRbeTJoevpNJcZxd","thumbnail_info":{"w":128,"h":128,"size":4522,"mimetype":"image/webp"}},"msgtype":"m.sticker","id":"mxc://matrix.axelchat.ru/WopBhzaqHCdbhofutrxqMaNI","net.maunium.telegram.sticker":null},{"body":"😿","url":"mxc://matrix.axelchat.ru/hctUnKWzfXrlkFASFvbHiimh","info":{"w":512,"h":512,"size":32586,"mimetype":"image/webp","thumbnail_url":"mxc://matrix.axelchat.ru/VOegKQFbfJDpLCNFFzNNpYbY","thumbnail_info":{"w":128,"h":128,"size":4876,"mimetype":"image/webp"}},"msgtype":"m.sticker","id":"mxc://matrix.axelchat.ru/hctUnKWzfXrlkFASFvbHiimh","net.maunium.telegram.sticker":null},{"body":"🍺","url":"mxc://matrix.axelchat.ru/gMroQCKFppNucctvIiBAMgMy","info":{"w":512,"h":511,"size":21322,"mimetype":"image/webp","thumbnail_url":"mxc://matrix.axelchat.ru/NkPyeGGKwaYkXzVkETIYitzU","thumbnail_info":{"w":128,"h":128,"size":4148,"mimetype":"image/webp"}},"msgtype":"m.sticker","id":"mxc://matrix.axelchat.ru/gMroQCKFppNucctvIiBAMgMy","net.maunium.telegram.sticker":null},{"body":"😖","url":"mxc://matrix.axelchat.ru/rhnsOtQPykYZSixDxlqSkRRi","info":{"w":512,"h":511,"size":21450,"mimetype":"image/webp","thumbnail_url":"mxc://matrix.axelchat.ru/AZOdcXFORmoLXVNIWUDPYJSC","thumbnail_info":{"w":128,"h":128,"size":4060,"mimetype":"image/webp"}},"msgtype":"m.sticker","id":"mxc://matrix.axelchat.ru/rhnsOtQPykYZSixDxlqSkRRi","net.maunium.telegram.sticker":null},{"body":"😏","url":"mxc://matrix.axelchat.ru/UJTKpyUQLeBSdYMPJUmxjJMS","info":{"w":512,"h":512,"size":32812,"mimetype":"image/webp","thumbnail_url":"mxc://matrix.axelchat.ru/YFBDHHAGLsCErIrJTHOHbjbi","thumbnail_info":{"w":128,"h":128,"size":5096,"mimetype":"image/webp"}},"msgtype":"m.sticker","id":"mxc://matrix.axelchat.ru/UJTKpyUQLeBSdYMPJUmxjJMS","net.maunium.telegram.sticker":null},{"body":"😒","url":"mxc://matrix.axelchat.ru/nHSqKgSpNYhQKVAFSsCijwzI","info":{"w":512,"h":512,"size":22142,"mimetype":"image/webp","thumbnail_url":"mxc://matrix.axelchat.ru/pFfpCRmIrzKwVpnoCSzJhPYh","thumbnail_info":{"w":128,"h":128,"size":3772,"mimetype":"image/webp"}},"msgtype":"m.sticker","id":"mxc://matrix.axelchat.ru/nHSqKgSpNYhQKVAFSsCijwzI","net.maunium.telegram.sticker":null},{"body":"🤧","url":"mxc://matrix.axelchat.ru/GJXhEquiAprGmoJrpdkybQqX","info":{"w":512,"h":512,"size":18456,"mimetype":"image/webp","thumbnail_url":"mxc://matrix.axelchat.ru/qVruAfNVMsZyYpWSBUQgutcW","thumbnail_info":{"w":320,"h":320,"size":9556,"mimetype":"image/webp"}},"msgtype":"m.sticker","id":"mxc://matrix.axelchat.ru/GJXhEquiAprGmoJrpdkybQqX","net.maunium.telegram.sticker":null},{"body":"😱","url":"mxc://matrix.axelchat.ru/PFkqfloiLlldNdomjFVfIChR","info":{"w":512,"h":512,"size":21200,"mimetype":"image/webp","thumbnail_url":"mxc://matrix.axelchat.ru/EtbyfcjNzhfbrVREdGtGUTFN","thumbnail_info":{"w":320,"h":320,"size":10572,"mimetype":"image/webp"}},"msgtype":"m.sticker","id":"mxc://matrix.axelchat.ru/PFkqfloiLlldNdomjFVfIChR","net.maunium.telegram.sticker":null},{"body":"😋","url":"mxc://matrix.axelchat.ru/ktekAMXxJXcEnjwSyQBLvTno","info":{"w":512,"h":512,"size":26290,"mimetype":"image/webp","thumbnail_url":"mxc://matrix.axelchat.ru/SaIVlTKblmItMkOQcWWBUyTB","thumbnail_info":{"w":320,"h":320,"size":12646,"mimetype":"image/webp"}},"msgtype":"m.sticker","id":"mxc://matrix.axelchat.ru/ktekAMXxJXcEnjwSyQBLvTno","net.maunium.telegram.sticker":null},{"body":"😤","url":"mxc://matrix.axelchat.ru/nmbFSZlKwWvcchHVAhJPGxQU","info":{"w":512,"h":512,"size":16084,"mimetype":"image/webp","thumbnail_url":"mxc://matrix.axelchat.ru/LtsGyiIMwtcJXvWgYHbbfWwl","thumbnail_info":{"w":320,"h":320,"size":9760,"mimetype":"image/webp"}},"msgtype":"m.sticker","id":"mxc://matrix.axelchat.ru/nmbFSZlKwWvcchHVAhJPGxQU","net.maunium.telegram.sticker":null},{"body":"😬","url":"mxc://matrix.axelchat.ru/tJFUaSPxPfqinNNUVSqxBoDq","info":{"w":512,"h":512,"size":32078,"mimetype":"image/webp","thumbnail_url":"mxc://matrix.axelchat.ru/tpjISpHaBQiaIOOAoLJzuFjT","thumbnail_info":{"w":320,"h":320,"size":16994,"mimetype":"image/webp"}},"msgtype":"m.sticker","id":"mxc://matrix.axelchat.ru/tJFUaSPxPfqinNNUVSqxBoDq","net.maunium.telegram.sticker":null},{"body":"🤑","url":"mxc://matrix.axelchat.ru/naNajJFHaAATsRQxjZLvufnx","info":{"w":512,"h":512,"size":28366,"mimetype":"image/webp","thumbnail_url":"mxc://matrix.axelchat.ru/eCtduZHcAgMbeDqvQQrqJaHc","thumbnail_info":{"w":320,"h":320,"size":13792,"mimetype":"image/webp"}},"msgtype":"m.sticker","id":"mxc://matrix.axelchat.ru/naNajJFHaAATsRQxjZLvufnx","net.maunium.telegram.sticker":null},{"body":"🤯","url":"mxc://matrix.axelchat.ru/KUvLjGdfOFvqAJTPYGBGSKjN","info":{"w":512,"h":512,"size":21914,"mimetype":"image/webp","thumbnail_url":"mxc://matrix.axelchat.ru/VGLKCvYRRKMLWZfHUfcBwprd","thumbnail_info":{"w":320,"h":320,"size":12214,"mimetype":"image/webp"}},"msgtype":"m.sticker","id":"mxc://matrix.axelchat.ru/KUvLjGdfOFvqAJTPYGBGSKjN","net.maunium.telegram.sticker":null},{"body":"🤬","url":"mxc://matrix.axelchat.ru/pgYMzNjDHoKxEGqFbPBWBrut","info":{"w":512,"h":512,"size":21276,"mimetype":"image/webp","thumbnail_url":"mxc://matrix.axelchat.ru/NpsodzBUHNxRjGnIVuDxiopp","thumbnail_info":{"w":320,"h":320,"size":11360,"mimetype":"image/webp"}},"msgtype":"m.sticker","id":"mxc://matrix.axelchat.ru/pgYMzNjDHoKxEGqFbPBWBrut","net.maunium.telegram.sticker":null},{"body":"👊","url":"mxc://matrix.axelchat.ru/TNFPSauBChnytdKEtERItEHr","info":{"w":512,"h":512,"size":26654,"mimetype":"image/webp","thumbnail_url":"mxc://matrix.axelchat.ru/zVXGRfSqoLKDwaKBvYDvnbuE","thumbnail_info":{"w":320,"h":320,"size":13458,"mimetype":"image/webp"}},"msgtype":"m.sticker","id":"mxc://matrix.axelchat.ru/TNFPSauBChnytdKEtERItEHr","net.maunium.telegram.sticker":null},{"body":"🤢","url":"mxc://matrix.axelchat.ru/hWmSblvxOReomQUuqafFhMlj","info":{"w":512,"h":512,"size":37722,"mimetype":"image/webp","thumbnail_url":"mxc://matrix.axelchat.ru/FxhSrZqyGHgjXrUegbwgRxSb","thumbnail_info":{"w":320,"h":320,"size":19452,"mimetype":"image/webp"}},"msgtype":"m.sticker","id":"mxc://matrix.axelchat.ru/hWmSblvxOReomQUuqafFhMlj","net.maunium.telegram.sticker":null},{"body":"🤘","url":"mxc://matrix.axelchat.ru/QxsrxvURDfPDLxNDSVMiEzwp","info":{"w":512,"h":512,"size":19792,"mimetype":"image/webp","thumbnail_url":"mxc://matrix.axelchat.ru/yYhWaUhwHhqWOPgTlIGpzfwe","thumbnail_info":{"w":320,"h":320,"size":11656,"mimetype":"image/webp"}},"msgtype":"m.sticker","id":"mxc://matrix.axelchat.ru/QxsrxvURDfPDLxNDSVMiEzwp","net.maunium.telegram.sticker":null},{"body":"😣","url":"mxc://matrix.axelchat.ru/kZuMEbHZZChyWVvdalSpHAkv","info":{"w":512,"h":512,"size":37728,"mimetype":"image/webp","thumbnail_url":"mxc://matrix.axelchat.ru/VSGGUSQOoSXQgsaAHTcnQJKl","thumbnail_info":{"w":320,"h":320,"size":18016,"mimetype":"image/webp"}},"msgtype":"m.sticker","id":"mxc://matrix.axelchat.ru/kZuMEbHZZChyWVvdalSpHAkv","net.maunium.telegram.sticker":null},{"body":"😡","url":"mxc://matrix.axelchat.ru/XhODaqzKBmDKDmGuwckMvJqm","info":{"w":512,"h":512,"size":32344,"mimetype":"image/webp","thumbnail_url":"mxc://matrix.axelchat.ru/eGpmOLRTVANdahLSlQMJkgJx","thumbnail_info":{"w":320,"h":320,"size":16428,"mimetype":"image/webp"}},"msgtype":"m.sticker","id":"mxc://matrix.axelchat.ru/XhODaqzKBmDKDmGuwckMvJqm","net.maunium.telegram.sticker":null},{"body":"💩","url":"mxc://matrix.axelchat.ru/mwFiYzsAbXBjzOBCJGGWIDBw","info":{"w":512,"h":512,"size":52860,"mimetype":"image/webp","thumbnail_url":"mxc://matrix.axelchat.ru/bUVunKPGNTUFmyazhaSbTAwh","thumbnail_info":{"w":320,"h":320,"size":25450,"mimetype":"image/webp"}},"msgtype":"m.sticker","id":"mxc://matrix.axelchat.ru/mwFiYzsAbXBjzOBCJGGWIDBw","net.maunium.telegram.sticker":null},{"body":"💃","url":"mxc://matrix.axelchat.ru/xDIFBIqQeVmugebtGmgkacFV","info":{"w":512,"h":512,"size":18082,"mimetype":"image/webp","thumbnail_url":"mxc://matrix.axelchat.ru/AYIrRanTIyecFJbhKDERyHzO","thumbnail_info":{"w":320,"h":320,"size":9336,"mimetype":"image/webp"}},"msgtype":"m.sticker","id":"mxc://matrix.axelchat.ru/xDIFBIqQeVmugebtGmgkacFV","net.maunium.telegram.sticker":null},{"body":"😭","url":"mxc://matrix.axelchat.ru/FdQQoVrMmLjfepvffBEXuXRS","info":{"w":512,"h":512,"size":15596,"mimetype":"image/webp","thumbnail_url":"mxc://matrix.axelchat.ru/SdVLMTNHTFKvhoiibeRSMUQI","thumbnail_info":{"w":320,"h":320,"size":8154,"mimetype":"image/webp"}},"msgtype":"m.sticker","id":"mxc://matrix.axelchat.ru/FdQQoVrMmLjfepvffBEXuXRS","net.maunium.telegram.sticker":null},{"body":"⚪️","url":"mxc://matrix.axelchat.ru/OzPZkMOGzgbOeQtCjTUEzUWV","info":{"w":512,"h":512,"size":17586,"mimetype":"image/webp","thumbnail_url":"mxc://matrix.axelchat.ru/ggaYbaxLSQhTSZAnZerMUQFo","thumbnail_info":{"w":320,"h":320,"size":10106,"mimetype":"image/webp"}},"msgtype":"m.sticker","id":"mxc://matrix.axelchat.ru/OzPZkMOGzgbOeQtCjTUEzUWV","net.maunium.telegram.sticker":null},{"body":"🎉","url":"mxc://matrix.axelchat.ru/RzwXpGbYlGqeQbAMaocrjPpG","info":{"w":512,"h":512,"size":18548,"mimetype":"image/webp","thumbnail_url":"mxc://matrix.axelchat.ru/MDMbCoYqnHqRbexiepVXEqNx","thumbnail_info":{"w":320,"h":320,"size":10038,"mimetype":"image/webp"}},"msgtype":"m.sticker","id":"mxc://matrix.axelchat.ru/RzwXpGbYlGqeQbAMaocrjPpG","net.maunium.telegram.sticker":null},{"body":"😁","url":"mxc://matrix.axelchat.ru/TmMuzRyeEGUjJiCTqbmcFkGg","info":{"w":512,"h":512,"size":12484,"mimetype":"image/webp","thumbnail_url":"mxc://matrix.axelchat.ru/YScztjmfuwtJxgOoWuvfTQwJ","thumbnail_info":{"w":320,"h":320,"size":7282,"mimetype":"image/webp"}},"msgtype":"m.sticker","id":"mxc://matrix.axelchat.ru/TmMuzRyeEGUjJiCTqbmcFkGg","net.maunium.telegram.sticker":null},{"body":"🤦","url":"mxc://matrix.axelchat.ru/mZHtPeKrsopvxrdxSumJUOhS","info":{"w":512,"h":512,"size":18138,"mimetype":"image/webp","thumbnail_url":"mxc://matrix.axelchat.ru/AlIRMnCULruqNyNRhugaXJDu","thumbnail_info":{"w":320,"h":320,"size":10274,"mimetype":"image/webp"}},"msgtype":"m.sticker","id":"mxc://matrix.axelchat.ru/mZHtPeKrsopvxrdxSumJUOhS","net.maunium.telegram.sticker":null},{"body":"👋","url":"mxc://matrix.axelchat.ru/GJLDDSQsREQHgXhDmnaPzSDL","info":{"w":512,"h":512,"size":17150,"mimetype":"image/webp","thumbnail_url":"mxc://matrix.axelchat.ru/BEwHgmFzNhbxgZiRgEQGDdwg","thumbnail_info":{"w":320,"h":320,"size":8920,"mimetype":"image/webp"}},"msgtype":"m.sticker","id":"mxc://matrix.axelchat.ru/GJLDDSQsREQHgXhDmnaPzSDL","net.maunium.telegram.sticker":null},{"body":"💂‍♀️","url":"mxc://matrix.axelchat.ru/mPhtiReDjgCdPvAsyqBDAlMK","info":{"w":512,"h":512,"size":18602,"mimetype":"image/webp","thumbnail_url":"mxc://matrix.axelchat.ru/AoIpvpcnqjoXYpucQVrnDPNy","thumbnail_info":{"w":320,"h":320,"size":9194,"mimetype":"image/webp"}},"msgtype":"m.sticker","id":"mxc://matrix.axelchat.ru/mPhtiReDjgCdPvAsyqBDAlMK","net.maunium.telegram.sticker":null},{"body":"👍","url":"mxc://matrix.axelchat.ru/GlkxBHkkTNQlCCMfzUbEUOXJ","info":{"w":512,"h":512,"size":27858,"mimetype":"image/webp","thumbnail_url":"mxc://matrix.axelchat.ru/ERaswpcIgkMJIkRCBdqDWjpR","thumbnail_info":{"w":320,"h":320,"size":14506,"mimetype":"image/webp"}},"msgtype":"m.sticker","id":"mxc://matrix.axelchat.ru/GlkxBHkkTNQlCCMfzUbEUOXJ","net.maunium.telegram.sticker":null},{"body":"👀","url":"mxc://matrix.axelchat.ru/tbmwWaDXADxxqeTteYTZtqXF","info":{"w":512,"h":512,"size":25550,"mimetype":"image/webp","thumbnail_url":"mxc://matrix.axelchat.ru/ocFkGnltbGiPoMaUkzRgIeKs","thumbnail_info":{"w":320,"h":320,"size":14096,"mimetype":"image/webp"}},"msgtype":"m.sticker","id":"mxc://matrix.axelchat.ru/tbmwWaDXADxxqeTteYTZtqXF","net.maunium.telegram.sticker":null},{"body":"🥵","url":"mxc://matrix.axelchat.ru/OnGbzNZVJphopZCfjOAzgarv","info":{"w":512,"h":512,"size":37064,"mimetype":"image/webp","thumbnail_url":"mxc://matrix.axelchat.ru/HQEtkMCbdFFnLJWcfoAnmYnp","thumbnail_info":{"w":320,"h":320,"size":19344,"mimetype":"image/webp"}},"msgtype":"m.sticker","id":"mxc://matrix.axelchat.ru/OnGbzNZVJphopZCfjOAzgarv","net.maunium.telegram.sticker":null},{"body":"❤️","url":"mxc://matrix.axelchat.ru/FSfUrJtwTcZQILRgDHZagajc","info":{"w":512,"h":512,"size":14350,"mimetype":"image/webp","thumbnail_url":"mxc://matrix.axelchat.ru/rrvufzinAXWFVmlZSddfLJLh","thumbnail_info":{"w":320,"h":320,"size":8380,"mimetype":"image/webp"}},"msgtype":"m.sticker","id":"mxc://matrix.axelchat.ru/FSfUrJtwTcZQILRgDHZagajc","net.maunium.telegram.sticker":null},{"body":"👹","url":"mxc://matrix.axelchat.ru/tJGavVjtQmlyOWbIPIUodiYU","info":{"w":512,"h":512,"size":12894,"mimetype":"image/webp","thumbnail_url":"mxc://matrix.axelchat.ru/ZbEaiPdnKrliagOMJcDVRcUt","thumbnail_info":{"w":320,"h":320,"size":7514,"mimetype":"image/webp"}},"msgtype":"m.sticker","id":"mxc://matrix.axelchat.ru/tJGavVjtQmlyOWbIPIUodiYU","net.maunium.telegram.sticker":null},{"body":"😳","url":"mxc://matrix.axelchat.ru/LNJIKQhqCaMctjziYHqnyPOS","info":{"w":512,"h":512,"size":19150,"mimetype":"image/webp","thumbnail_url":"mxc://matrix.axelchat.ru/RotRlhiuOcDgILGLESQXxsuW","thumbnail_info":{"w":320,"h":320,"size":10148,"mimetype":"image/webp"}},"msgtype":"m.sticker","id":"mxc://matrix.axelchat.ru/LNJIKQhqCaMctjziYHqnyPOS","net.maunium.telegram.sticker":null},{"body":"😔","url":"mxc://matrix.axelchat.ru/AnbLTlfsEWSYcSnqXyJwunNZ","info":{"w":512,"h":512,"size":43114,"mimetype":"image/webp","thumbnail_url":"mxc://matrix.axelchat.ru/iUOibSmrDjvswtzedrHnCbnR","thumbnail_info":{"w":320,"h":320,"size":20684,"mimetype":"image/webp"}},"msgtype":"m.sticker","id":"mxc://matrix.axelchat.ru/AnbLTlfsEWSYcSnqXyJwunNZ","net.maunium.telegram.sticker":null},{"body":"💩","url":"mxc://matrix.axelchat.ru/FFuPKLuPFdopPhpOWjPTCSNh","info":{"w":512,"h":512,"size":17788,"mimetype":"image/webp","thumbnail_url":"mxc://matrix.axelchat.ru/NRjLidRqvfbZLAXjnyHAmkWS","thumbnail_info":{"w":320,"h":320,"size":10110,"mimetype":"image/webp"}},"msgtype":"m.sticker","id":"mxc://matrix.axelchat.ru/FFuPKLuPFdopPhpOWjPTCSNh","net.maunium.telegram.sticker":null},{"body":"🤪","url":"mxc://matrix.axelchat.ru/ZbojrLcDzPDGgqqIziKigjcy","info":{"w":512,"h":512,"size":15414,"mimetype":"image/webp","thumbnail_url":"mxc://matrix.axelchat.ru/QfQcEnIwmmJUxwDCUEaCiOcx","thumbnail_info":{"w":320,"h":320,"size":8586,"mimetype":"image/webp"}},"msgtype":"m.sticker","id":"mxc://matrix.axelchat.ru/ZbojrLcDzPDGgqqIziKigjcy","net.maunium.telegram.sticker":null},{"body":"❌","url":"mxc://matrix.axelchat.ru/XdrBTDzhGyXQaoLTJhCuIolS","info":{"w":512,"h":512,"size":36918,"mimetype":"image/webp","thumbnail_url":"mxc://matrix.axelchat.ru/rysHWjZlBssDmfsbKDyhYrYU","thumbnail_info":{"w":320,"h":320,"size":18152,"mimetype":"image/webp"}},"msgtype":"m.sticker","id":"mxc://matrix.axelchat.ru/XdrBTDzhGyXQaoLTJhCuIolS","net.maunium.telegram.sticker":null},{"body":"👽","url":"mxc://matrix.axelchat.ru/gigaveRvNheoNJpfacCHFGFH","info":{"w":512,"h":512,"size":14572,"mimetype":"image/webp","thumbnail_url":"mxc://matrix.axelchat.ru/trImBkLcmngfpDqRITIpGNPV","thumbnail_info":{"w":320,"h":320,"size":9054,"mimetype":"image/webp"}},"msgtype":"m.sticker","id":"mxc://matrix.axelchat.ru/gigaveRvNheoNJpfacCHFGFH","net.maunium.telegram.sticker":null},{"body":"🙁","url":"mxc://matrix.axelchat.ru/ruUJqZKehBbAHrOgVpPIyHbG","info":{"w":512,"h":512,"size":31046,"mimetype":"image/webp","thumbnail_url":"mxc://matrix.axelchat.ru/XfsfXfrmWHlliNCncWhJXlcK","thumbnail_info":{"w":320,"h":320,"size":13302,"mimetype":"image/webp"}},"msgtype":"m.sticker","id":"mxc://matrix.axelchat.ru/ruUJqZKehBbAHrOgVpPIyHbG","net.maunium.telegram.sticker":null},{"body":"🤝","url":"mxc://matrix.axelchat.ru/gPaazfEtCqUJcGqqWVXgCHkz","info":{"w":512,"h":512,"size":23236,"mimetype":"image/webp","thumbnail_url":"mxc://matrix.axelchat.ru/POtOlWzsphEuDbCyznPCkWCW","thumbnail_info":{"w":320,"h":320,"size":13192,"mimetype":"image/webp"}},"msgtype":"m.sticker","id":"mxc://matrix.axelchat.ru/gPaazfEtCqUJcGqqWVXgCHkz","net.maunium.telegram.sticker":null},{"body":"🥳","url":"mxc://matrix.axelchat.ru/TmskxwCjiGislGXlQwPHAIZu","info":{"w":512,"h":512,"size":22370,"mimetype":"image/webp","thumbnail_url":"mxc://matrix.axelchat.ru/eqhriGWrjJlsKJWjaICwyndB","thumbnail_info":{"w":320,"h":320,"size":11192,"mimetype":"image/webp"}},"msgtype":"m.sticker","id":"mxc://matrix.axelchat.ru/TmskxwCjiGislGXlQwPHAIZu","net.maunium.telegram.sticker":null},{"body":"👋","url":"mxc://matrix.axelchat.ru/jPpZPxPVxunZbdyAPDeudriC","info":{"w":512,"h":512,"size":32894,"mimetype":"image/webp","thumbnail_url":"mxc://matrix.axelchat.ru/ezdKzZRgCXRWEWHWTDGQqrKN","thumbnail_info":{"w":320,"h":320,"size":17488,"mimetype":"image/webp"}},"msgtype":"m.sticker","id":"mxc://matrix.axelchat.ru/jPpZPxPVxunZbdyAPDeudriC","net.maunium.telegram.sticker":null},{"body":"❤️","url":"mxc://matrix.axelchat.ru/UDLktATWYVfSUCqTUzCaqanO","info":{"w":512,"h":512,"size":18124,"mimetype":"image/webp","thumbnail_url":"mxc://matrix.axelchat.ru/rwUQuNDJXkoIDzfJZytqjqPV","thumbnail_info":{"w":320,"h":320,"size":10402,"mimetype":"image/webp"}},"msgtype":"m.sticker","id":"mxc://matrix.axelchat.ru/UDLktATWYVfSUCqTUzCaqanO","net.maunium.telegram.sticker":null},{"body":"😎","url":"mxc://matrix.axelchat.ru/iTDPjNWJhzCZQLWPAxtHpAHy","info":{"w":512,"h":512,"size":22290,"mimetype":"image/webp","thumbnail_url":"mxc://matrix.axelchat.ru/qBOnERlJrrCnhTuBIlzkyXcm","thumbnail_info":{"w":320,"h":320,"size":12360,"mimetype":"image/webp"}},"msgtype":"m.sticker","id":"mxc://matrix.axelchat.ru/iTDPjNWJhzCZQLWPAxtHpAHy","net.maunium.telegram.sticker":null},{"body":"💀","url":"mxc://matrix.axelchat.ru/INoEOTyPzzCqzdKCPyprasyY","info":{"w":512,"h":512,"size":18262,"mimetype":"image/webp","thumbnail_url":"mxc://matrix.axelchat.ru/aZTjjDNoJlhEiojRPwyvaCsb","thumbnail_info":{"w":320,"h":320,"size":9392,"mimetype":"image/webp"}},"msgtype":"m.sticker","id":"mxc://matrix.axelchat.ru/INoEOTyPzzCqzdKCPyprasyY","net.maunium.telegram.sticker":null},{"body":"😀","url":"mxc://matrix.axelchat.ru/nUnARsljVfbeOCEMGNeSgIWI","info":{"w":512,"h":512,"size":50464,"mimetype":"image/webp","thumbnail_url":"mxc://matrix.axelchat.ru/VzuOZCHvICBpktqjghMrERCH","thumbnail_info":{"w":320,"h":320,"size":22090,"mimetype":"image/webp"}},"msgtype":"m.sticker","id":"mxc://matrix.axelchat.ru/nUnARsljVfbeOCEMGNeSgIWI","net.maunium.telegram.sticker":null},{"body":"😡","url":"mxc://matrix.axelchat.ru/PVMENhDeXeJHRYGfGURdxZad","info":{"w":512,"h":512,"size":17242,"mimetype":"image/webp","thumbnail_url":"mxc://matrix.axelchat.ru/gcpRfFmkOBRFbLbFDkLRIzNv","thumbnail_info":{"w":320,"h":320,"size":10374,"mimetype":"image/webp"}},"msgtype":"m.sticker","id":"mxc://matrix.axelchat.ru/PVMENhDeXeJHRYGfGURdxZad","net.maunium.telegram.sticker":null},{"body":"🥺","url":"mxc://matrix.axelchat.ru/snqLLcljZdwbEBYEJkBmkDGu","info":{"w":512,"h":512,"size":13044,"mimetype":"image/webp","thumbnail_url":"mxc://matrix.axelchat.ru/IlnftsUBoSNebRvZwXfRNHeh","thumbnail_info":{"w":320,"h":320,"size":6638,"mimetype":"image/webp"}},"msgtype":"m.sticker","id":"mxc://matrix.axelchat.ru/snqLLcljZdwbEBYEJkBmkDGu","net.maunium.telegram.sticker":null},{"body":"🤣","url":"mxc://matrix.axelchat.ru/oXkjvQCAatlLmzCnYWSlHStd","info":{"w":512,"h":512,"size":12142,"mimetype":"image/webp","thumbnail_url":"mxc://matrix.axelchat.ru/kFMQqowAtpmOZDuccmWvTqgu","thumbnail_info":{"w":320,"h":320,"size":7880,"mimetype":"image/webp"}},"msgtype":"m.sticker","id":"mxc://matrix.axelchat.ru/oXkjvQCAatlLmzCnYWSlHStd","net.maunium.telegram.sticker":null},{"body":"👋","url":"mxc://matrix.axelchat.ru/rDhlgVcQxpkZDWUtjDPmrulS","info":{"w":512,"h":512,"size":24188,"mimetype":"image/webp","thumbnail_url":"mxc://matrix.axelchat.ru/eyruZjZUZhHsTbnfZULhbAVn","thumbnail_info":{"w":320,"h":320,"size":13122,"mimetype":"image/webp"}},"msgtype":"m.sticker","id":"mxc://matrix.axelchat.ru/rDhlgVcQxpkZDWUtjDPmrulS","net.maunium.telegram.sticker":null},{"body":"🤨","url":"mxc://matrix.axelchat.ru/RtHxDGhRzRXGUfoZTJnafEMH","info":{"w":512,"h":512,"size":17688,"mimetype":"image/webp","thumbnail_url":"mxc://matrix.axelchat.ru/YtzyFAFISUqzoARTVFUkkdvq","thumbnail_info":{"w":320,"h":320,"size":10646,"mimetype":"image/webp"}},"msgtype":"m.sticker","id":"mxc://matrix.axelchat.ru/RtHxDGhRzRXGUfoZTJnafEMH","net.maunium.telegram.sticker":null},{"body":"😳","url":"mxc://matrix.axelchat.ru/QKKjtBRLQpfsPVXgytfnuyMw","info":{"w":512,"h":512,"size":11004,"mimetype":"image/webp","thumbnail_url":"mxc://matrix.axelchat.ru/OuQDalIKGyhsAqcGYipcNyVb","thumbnail_info":{"w":320,"h":320,"size":7266,"mimetype":"image/webp"}},"msgtype":"m.sticker","id":"mxc://matrix.axelchat.ru/QKKjtBRLQpfsPVXgytfnuyMw","net.maunium.telegram.sticker":null}]}