{"title":"Лягуш Пип (@TgSticker)","id":"tg_name_pip_vk","net.maunium.telegram.pack":null,"stickers":[{"body":"👋","url":"mxc://matrix.axelchat.ru/uKuMwKmkQZsGTonIlfkaJRzh","info":{"w":512,"h":512,"size":7848860,"mimetype":"image/webp","thumbnail_url":"mxc://matrix.axelchat.ru/rEFzZgDPyHCzTDdPAzmSoCuW","thumbnail_info":{"w":128,"h":128,"size":6698,"mimetype":"image/webp"}},"msgtype":"m.sticker","id":"mxc://matrix.axelchat.ru/uKuMwKmkQZsGTonIlfkaJRzh","net.maunium.telegram.sticker":null},{"body":"😉","url":"mxc://matrix.axelchat.ru/vLJFPfBYQSUcewbslQeDZBGy","info":{"w":512,"h":512,"size":5806752,"mimetype":"image/webp","thumbnail_url":"mxc://matrix.axelchat.ru/PsfGpuWfJtwoKeEcOQSvlJMc","thumbnail_info":{"w":128,"h":128,"size":5546,"mimetype":"image/webp"}},"msgtype":"m.sticker","id":"mxc://matrix.axelchat.ru/vLJFPfBYQSUcewbslQeDZBGy","net.maunium.telegram.sticker":null},{"body":"🖕","url":"mxc://matrix.axelchat.ru/jTmqKCkpurmraWGrgfLHHTOZ","info":{"w":512,"h":512,"size":4440702,"mimetype":"image/webp","thumbnail_url":"mxc://matrix.axelchat.ru/FYmKLcMEDxxpBTAgkPURaSKp","thumbnail_info":{"w":128,"h":128,"size":4470,"mimetype":"image/webp"}},"msgtype":"m.sticker","id":"mxc://matrix.axelchat.ru/jTmqKCkpurmraWGrgfLHHTOZ","net.maunium.telegram.sticker":null},{"body":"😍","url":"mxc://matrix.axelchat.ru/EGIqxHhxMEViSVoPodvJsdyM","info":{"w":512,"h":512,"size":6171490,"mimetype":"image/webp","thumbnail_url":"mxc://matrix.axelchat.ru/flNBHcdoWGewtGuavUSrUlCc","thumbnail_info":{"w":128,"h":128,"size":6460,"mimetype":"image/webp"}},"msgtype":"m.sticker","id":"mxc://matrix.axelchat.ru/EGIqxHhxMEViSVoPodvJsdyM","net.maunium.telegram.sticker":null},{"body":"😭","url":"mxc://matrix.axelchat.ru/XwywQFrOwMhkCWumXgzNfWuN","info":{"w":512,"h":512,"size":6451952,"mimetype":"image/webp","thumbnail_url":"mxc://matrix.axelchat.ru/HLoiIfjIGOaeVqYVRXUwDBnp","thumbnail_info":{"w":128,"h":128,"size":5694,"mimetype":"image/webp"}},"msgtype":"m.sticker","id":"mxc://matrix.axelchat.ru/XwywQFrOwMhkCWumXgzNfWuN","net.maunium.telegram.sticker":null},{"body":"🤩","url":"mxc://matrix.axelchat.ru/fMOOVzcVSYbkWXKXRSNEKmiT","info":{"w":512,"h":512,"size":5362372,"mimetype":"image/webp","thumbnail_url":"mxc://matrix.axelchat.ru/SgtNLqfpxRxOgQWIspkCoaDV","thumbnail_info":{"w":128,"h":128,"size":5968,"mimetype":"image/webp"}},"msgtype":"m.sticker","id":"mxc://matrix.axelchat.ru/fMOOVzcVSYbkWXKXRSNEKmiT","net.maunium.telegram.sticker":null},{"body":"🥺","url":"mxc://matrix.axelchat.ru/DCcswBSgHFPYEiiIcfcMZPVA","info":{"w":512,"h":512,"size":7737424,"mimetype":"image/webp","thumbnail_url":"mxc://matrix.axelchat.ru/qFJznTAFcUuPBvLgFkVGUHra","thumbnail_info":{"w":128,"h":128,"size":9338,"mimetype":"image/webp"}},"msgtype":"m.sticker","id":"mxc://matrix.axelchat.ru/DCcswBSgHFPYEiiIcfcMZPVA","net.maunium.telegram.sticker":null},{"body":"😴","url":"mxc://matrix.axelchat.ru/PTxrRQDaqJsNbQVZpSsmQPXe","info":{"w":512,"h":512,"size":6656276,"mimetype":"image/webp","thumbnail_url":"mxc://matrix.axelchat.ru/bJpAQWvkNYMmObpKBYFSjgWx","thumbnail_info":{"w":128,"h":128,"size":5434,"mimetype":"image/webp"}},"msgtype":"m.sticker","id":"mxc://matrix.axelchat.ru/PTxrRQDaqJsNbQVZpSsmQPXe","net.maunium.telegram.sticker":null},{"body":"😭","url":"mxc://matrix.axelchat.ru/rtVmvyiyRxAGitRAqWLPbSdZ","info":{"w":512,"h":512,"size":10779718,"mimetype":"image/webp","thumbnail_url":"mxc://matrix.axelchat.ru/bwMbPlMaRUAfFalhzZOicuIy","thumbnail_info":{"w":128,"h":128,"size":7872,"mimetype":"image/webp"}},"msgtype":"m.sticker","id":"mxc://matrix.axelchat.ru/rtVmvyiyRxAGitRAqWLPbSdZ","net.maunium.telegram.sticker":null},{"body":"👍","url":"mxc://matrix.axelchat.ru/MYvTOvpfJWsMmVTFLqnDUIGO","info":{"w":512,"h":512,"size":6124118,"mimetype":"image/webp","thumbnail_url":"mxc://matrix.axelchat.ru/MiAmaOiKFggsILxwktjyifda","thumbnail_info":{"w":128,"h":128,"size":6036,"mimetype":"image/webp"}},"msgtype":"m.sticker","id":"mxc://matrix.axelchat.ru/MYvTOvpfJWsMmVTFLqnDUIGO","net.maunium.telegram.sticker":null},{"body":"😳","url":"mxc://matrix.axelchat.ru/jQOVEhNyGXkHbhJhIsodclED","info":{"w":512,"h":512,"size":5712296,"mimetype":"image/webp","thumbnail_url":"mxc://matrix.axelchat.ru/dqoKtwTfEuKbpOEwwDlvQYQd","thumbnail_info":{"w":128,"h":128,"size":5226,"mimetype":"image/webp"}},"msgtype":"m.sticker","id":"mxc://matrix.axelchat.ru/jQOVEhNyGXkHbhJhIsodclED","net.maunium.telegram.sticker":null},{"body":"🍿","url":"mxc://matrix.axelchat.ru/dqOiCBzUayCWUsBfmIdwdbgs","info":{"w":512,"h":512,"size":8281308,"mimetype":"image/webp","thumbnail_url":"mxc://matrix.axelchat.ru/FqZmDWnkiLzgDntIiDwDNpvg","thumbnail_info":{"w":128,"h":128,"size":7438,"mimetype":"image/webp"}},"msgtype":"m.sticker","id":"mxc://matrix.axelchat.ru/dqOiCBzUayCWUsBfmIdwdbgs","net.maunium.telegram.sticker":null},{"body":"🧙‍♂","url":"mxc://matrix.axelchat.ru/fUSPWMKmDJFdXiOpRcCrrzmJ","info":{"w":512,"h":512,"size":9097334,"mimetype":"image/webp","thumbnail_url":"mxc://matrix.axelchat.ru/vXwtXVtWGKtQUFHMgyBYTJjF","thumbnail_info":{"w":128,"h":128,"size":8338,"mimetype":"image/webp"}},"msgtype":"m.sticker","id":"mxc://matrix.axelchat.ru/fUSPWMKmDJFdXiOpRcCrrzmJ","net.maunium.telegram.sticker":null},{"body":"😡","url":"mxc://matrix.axelchat.ru/kZSFmuKZRBxiDZYFimsxdTvK","info":{"w":512,"h":512,"size":3862282,"mimetype":"image/webp","thumbnail_url":"mxc://matrix.axelchat.ru/bcShxSgapoPErWssEgmxspkU","thumbnail_info":{"w":128,"h":128,"size":4352,"mimetype":"image/webp"}},"msgtype":"m.sticker","id":"mxc://matrix.axelchat.ru/kZSFmuKZRBxiDZYFimsxdTvK","net.maunium.telegram.sticker":null},{"body":"👎","url":"mxc://matrix.axelchat.ru/CHcWFNDdxHYdEvzWKmSMKVbB","info":{"w":512,"h":512,"size":6687510,"mimetype":"image/webp","thumbnail_url":"mxc://matrix.axelchat.ru/fvwZImiwHxtliiRAruVTdiIR","thumbnail_info":{"w":128,"h":128,"size":5684,"mimetype":"image/webp"}},"msgtype":"m.sticker","id":"mxc://matrix.axelchat.ru/CHcWFNDdxHYdEvzWKmSMKVbB","net.maunium.telegram.sticker":null},{"body":"😵‍💫","url":"mxc://matrix.axelchat.ru/JTrugkropnLMUzfGtIQEUjdZ","info":{"w":512,"h":512,"size":6418708,"mimetype":"image/webp","thumbnail_url":"mxc://matrix.axelchat.ru/XYXUGBOxxgqfgwSpyCcXIMHW","thumbnail_info":{"w":128,"h":128,"size":6654,"mimetype":"image/webp"}},"msgtype":"m.sticker","id":"mxc://matrix.axelchat.ru/JTrugkropnLMUzfGtIQEUjdZ","net.maunium.telegram.sticker":null},{"body":"☕️","url":"mxc://matrix.axelchat.ru/zOKaEfthplyQbTFAyxwlFkQN","info":{"w":512,"h":512,"size":5823440,"mimetype":"image/webp","thumbnail_url":"mxc://matrix.axelchat.ru/YFRtXvbEgVsDXLVOPJQTMCso","thumbnail_info":{"w":128,"h":128,"size":6148,"mimetype":"image/webp"}},"msgtype":"m.sticker","id":"mxc://matrix.axelchat.ru/zOKaEfthplyQbTFAyxwlFkQN","net.maunium.telegram.sticker":null},{"body":"🕷","url":"mxc://matrix.axelchat.ru/RdmEsCyLIeZsRDeTSFaTeCuk","info":{"w":512,"h":512,"size":5277214,"mimetype":"image/webp","thumbnail_url":"mxc://matrix.axelchat.ru/vyYKhyisySvxAIyKMCQQeRRI","thumbnail_info":{"w":128,"h":128,"size":5228,"mimetype":"image/webp"}},"msgtype":"m.sticker","id":"mxc://matrix.axelchat.ru/RdmEsCyLIeZsRDeTSFaTeCuk","net.maunium.telegram.sticker":null},{"body":"🥺","url":"mxc://matrix.axelchat.ru/aoiQRmRzkNcMIExFjxEmKHQw","info":{"w":512,"h":512,"size":4967736,"mimetype":"image/webp","thumbnail_url":"mxc://matrix.axelchat.ru/nMCFGEFfokFJJbyZgJGBCgvA","thumbnail_info":{"w":128,"h":128,"size":5542,"mimetype":"image/webp"}},"msgtype":"m.sticker","id":"mxc://matrix.axelchat.ru/aoiQRmRzkNcMIExFjxEmKHQw","net.maunium.telegram.sticker":null},{"body":"😐","url":"mxc://matrix.axelchat.ru/PEsGbWCtOfrqLJOliWjeMBiY","info":{"w":512,"h":512,"size":7573964,"mimetype":"image/webp","thumbnail_url":"mxc://matrix.axelchat.ru/CQLntaUfRtUUxoSrqMaaAVSN","thumbnail_info":{"w":128,"h":128,"size":6946,"mimetype":"image/webp"}},"msgtype":"m.sticker","id":"mxc://matrix.axelchat.ru/PEsGbWCtOfrqLJOliWjeMBiY","net.maunium.telegram.sticker":null},{"body":"😬","url":"mxc://matrix.axelchat.ru/JAUallOlDLCWJeJezJfxzjgW","info":{"w":512,"h":512,"size":6713160,"mimetype":"image/webp","thumbnail_url":"mxc://matrix.axelchat.ru/rSxwuJHYXJzXPVjhmfLKZqRY","thumbnail_info":{"w":128,"h":128,"size":6096,"mimetype":"image/webp"}},"msgtype":"m.sticker","id":"mxc://matrix.axelchat.ru/JAUallOlDLCWJeJezJfxzjgW","net.maunium.telegram.sticker":null},{"body":"💔","url":"mxc://matrix.axelchat.ru/PSXcnXOzfHgGsEbgXGiYDjqM","info":{"w":512,"h":512,"size":7601552,"mimetype":"image/webp","thumbnail_url":"mxc://matrix.axelchat.ru/SgEaqsDOlMFmAaZlGrfbtIme","thumbnail_info":{"w":128,"h":128,"size":6494,"mimetype":"image/webp"}},"msgtype":"m.sticker","id":"mxc://matrix.axelchat.ru/PSXcnXOzfHgGsEbgXGiYDjqM","net.maunium.telegram.sticker":null},{"body":"🪰","url":"mxc://matrix.axelchat.ru/NefnEEyTESkbtgKGJAvdZjwH","info":{"w":512,"h":512,"size":4790468,"mimetype":"image/webp","thumbnail_url":"mxc://matrix.axelchat.ru/OfieOzVeHeVJRJKAmdrxfyQH","thumbnail_info":{"w":128,"h":128,"size":6230,"mimetype":"image/webp"}},"msgtype":"m.sticker","id":"mxc://matrix.axelchat.ru/NefnEEyTESkbtgKGJAvdZjwH","net.maunium.telegram.sticker":null},{"body":"👀","url":"mxc://matrix.axelchat.ru/cBbVxsTiSkqMskIhwzTQkudR","info":{"w":512,"h":512,"size":7426246,"mimetype":"image/webp","thumbnail_url":"mxc://matrix.axelchat.ru/IPlXtJYePkoGquKoDHkIKcIF","thumbnail_info":{"w":128,"h":128,"size":5964,"mimetype":"image/webp"}},"msgtype":"m.sticker","id":"mxc://matrix.axelchat.ru/cBbVxsTiSkqMskIhwzTQkudR","net.maunium.telegram.sticker":null},{"body":"👌","url":"mxc://matrix.axelchat.ru/oOivOAadnnYqtMPgacxVZuRy","info":{"w":512,"h":512,"size":4693634,"mimetype":"image/webp","thumbnail_url":"mxc://matrix.axelchat.ru/pazazXkkmENgaqFtYDyGuyaj","thumbnail_info":{"w":128,"h":128,"size":4680,"mimetype":"image/webp"}},"msgtype":"m.sticker","id":"mxc://matrix.axelchat.ru/oOivOAadnnYqtMPgacxVZuRy","net.maunium.telegram.sticker":null},{"body":"🤩","url":"mxc://matrix.axelchat.ru/DtnIXgfgMjCNvVzrneSrnUaY","info":{"w":512,"h":512,"size":4597390,"mimetype":"image/webp","thumbnail_url":"mxc://matrix.axelchat.ru/LEhyziupEXpBzIgjBQWNecJL","thumbnail_info":{"w":128,"h":128,"size":5046,"mimetype":"image/webp"}},"msgtype":"m.sticker","id":"mxc://matrix.axelchat.ru/DtnIXgfgMjCNvVzrneSrnUaY","net.maunium.telegram.sticker":null},{"body":"🤦‍♂","url":"mxc://matrix.axelchat.ru/nWNcSdllwabRibHaaLhtyany","info":{"w":512,"h":512,"size":5358362,"mimetype":"image/webp","thumbnail_url":"mxc://matrix.axelchat.ru/ZftKdAEEFEmGOpQfASTzfHWG","thumbnail_info":{"w":128,"h":128,"size":4948,"mimetype":"image/webp"}},"msgtype":"m.sticker","id":"mxc://matrix.axelchat.ru/nWNcSdllwabRibHaaLhtyany","net.maunium.telegram.sticker":null},{"body":"😟","url":"mxc://matrix.axelchat.ru/TLqdsRdZSGvJVBSTUQqVPUlr","info":{"w":512,"h":512,"size":4905910,"mimetype":"image/webp","thumbnail_url":"mxc://matrix.axelchat.ru/IJbpNgGJzJfSwDMCZmkUdgaM","thumbnail_info":{"w":128,"h":128,"size":7190,"mimetype":"image/webp"}},"msgtype":"m.sticker","id":"mxc://matrix.axelchat.ru/TLqdsRdZSGvJVBSTUQqVPUlr","net.maunium.telegram.sticker":null},{"body":"💃","url":"mxc://matrix.axelchat.ru/WJEZkRchWDHqRUGsalJPOapP","info":{"w":512,"h":512,"size":5681102,"mimetype":"image/webp","thumbnail_url":"mxc://matrix.axelchat.ru/cpecJGpYWndvoxpdqJmWtPBs","thumbnail_info":{"w":128,"h":128,"size":5558,"mimetype":"image/webp"}},"msgtype":"m.sticker","id":"mxc://matrix.axelchat.ru/WJEZkRchWDHqRUGsalJPOapP","net.maunium.telegram.sticker":null},{"body":"😦","url":"mxc://matrix.axelchat.ru/MkWsrMjUfHQvoSuWixWFnClp","info":{"w":512,"h":512,"size":5332624,"mimetype":"image/webp","thumbnail_url":"mxc://matrix.axelchat.ru/HjLywMxKEZoZnDLLyJZioADp","thumbnail_info":{"w":128,"h":128,"size":6228,"mimetype":"image/webp"}},"msgtype":"m.sticker","id":"mxc://matrix.axelchat.ru/MkWsrMjUfHQvoSuWixWFnClp","net.maunium.telegram.sticker":null},{"body":"🤪","url":"mxc://matrix.axelchat.ru/pGWdUiSwpzIHpEUdxpDVQcYC","info":{"w":512,"h":512,"size":5949530,"mimetype":"image/webp","thumbnail_url":"mxc://matrix.axelchat.ru/mHmYiplsWndVAfqdrtPybZXx","thumbnail_info":{"w":128,"h":128,"size":5722,"mimetype":"image/webp"}},"msgtype":"m.sticker","id":"mxc://matrix.axelchat.ru/pGWdUiSwpzIHpEUdxpDVQcYC","net.maunium.telegram.sticker":null},{"body":"🙅‍♀️","url":"mxc://matrix.axelchat.ru/CxCApJGNylbFlbcwKNzkaONN","info":{"w":512,"h":512,"size":4800052,"mimetype":"image/webp","thumbnail_url":"mxc://matrix.axelchat.ru/UsokhsFSUYLBIsVrCVSyTSsx","thumbnail_info":{"w":128,"h":128,"size":5322,"mimetype":"image/webp"}},"msgtype":"m.sticker","id":"mxc://matrix.axelchat.ru/CxCApJGNylbFlbcwKNzkaONN","net.maunium.telegram.sticker":null},{"body":"😂","url":"mxc://matrix.axelchat.ru/gcGosnzPmlUBnNoMDebIAeGc","info":{"w":512,"h":512,"size":5940612,"mimetype":"image/webp","thumbnail_url":"mxc://matrix.axelchat.ru/PxItISISPcpvGfAyGTuMNRoM","thumbnail_info":{"w":128,"h":128,"size":5296,"mimetype":"image/webp"}},"msgtype":"m.sticker","id":"mxc://matrix.axelchat.ru/gcGosnzPmlUBnNoMDebIAeGc","net.maunium.telegram.sticker":null},{"body":"🤔","url":"mxc://matrix.axelchat.ru/CUuayaFdbceMdisjKPExmnPV","info":{"w":512,"h":512,"size":5136564,"mimetype":"image/webp","thumbnail_url":"mxc://matrix.axelchat.ru/CQduXIaBefZvCyoyRbfipclJ","thumbnail_info":{"w":128,"h":128,"size":5354,"mimetype":"image/webp"}},"msgtype":"m.sticker","id":"mxc://matrix.axelchat.ru/CUuayaFdbceMdisjKPExmnPV","net.maunium.telegram.sticker":null},{"body":"💃","url":"mxc://matrix.axelchat.ru/wClwWJneRNfShtXfBmuEtWMM","info":{"w":512,"h":512,"size":5165658,"mimetype":"image/webp","thumbnail_url":"mxc://matrix.axelchat.ru/IBwGWNkTyvtrwJPuXbvoBICG","thumbnail_info":{"w":128,"h":128,"size":5208,"mimetype":"image/webp"}},"msgtype":"m.sticker","id":"mxc://matrix.axelchat.ru/wClwWJneRNfShtXfBmuEtWMM","net.maunium.telegram.sticker":null},{"body":"😎","url":"mxc://matrix.axelchat.ru/EXIRyBBMzRRBsyaVmJnxRiPl","info":{"w":512,"h":512,"size":8470824,"mimetype":"image/webp","thumbnail_url":"mxc://matrix.axelchat.ru/AIVxqYZoRfuaBjxKQynfhqNo","thumbnail_info":{"w":128,"h":128,"size":6322,"mimetype":"image/webp"}},"msgtype":"m.sticker","id":"mxc://matrix.axelchat.ru/EXIRyBBMzRRBsyaVmJnxRiPl","net.maunium.telegram.sticker":null},{"body":"🤨","url":"mxc://matrix.axelchat.ru/ZtQtwhboKNtpefiBWrMeGFrJ","info":{"w":512,"h":512,"size":5256116,"mimetype":"image/webp","thumbnail_url":"mxc://matrix.axelchat.ru/OsuVUpcouFBDSvhfXQDqNSOY","thumbnail_info":{"w":128,"h":128,"size":4894,"mimetype":"image/webp"}},"msgtype":"m.sticker","id":"mxc://matrix.axelchat.ru/ZtQtwhboKNtpefiBWrMeGFrJ","net.maunium.telegram.sticker":null},{"body":"🌈","url":"mxc://matrix.axelchat.ru/hHTsaEYNnTqgWcGAxVBqXWNq","info":{"w":512,"h":512,"size":5783364,"mimetype":"image/webp","thumbnail_url":"mxc://matrix.axelchat.ru/ccGVSAzNepDmzRvoBvXTZqQX","thumbnail_info":{"w":128,"h":128,"size":6790,"mimetype":"image/webp"}},"msgtype":"m.sticker","id":"mxc://matrix.axelchat.ru/hHTsaEYNnTqgWcGAxVBqXWNq","net.maunium.telegram.sticker":null},{"body":"🤪","url":"mxc://matrix.axelchat.ru/NUmMNaOLyOssNXJjifSMqiim","info":{"w":512,"h":512,"size":8332878,"mimetype":"image/webp","thumbnail_url":"mxc://matrix.axelchat.ru/GQiihRMWfastKKibSeIUrbcp","thumbnail_info":{"w":128,"h":128,"size":6816,"mimetype":"image/webp"}},"msgtype":"m.sticker","id":"mxc://matrix.axelchat.ru/NUmMNaOLyOssNXJjifSMqiim","net.maunium.telegram.sticker":null},{"body":"🌸","url":"mxc://matrix.axelchat.ru/CGLoWlTaqmQkAZVoCDAPsOCh","info":{"w":512,"h":512,"size":6457080,"mimetype":"image/webp","thumbnail_url":"mxc://matrix.axelchat.ru/DWVInbGCMOFUXNRTxohmThlk","thumbnail_info":{"w":128,"h":128,"size":4406,"mimetype":"image/webp"}},"msgtype":"m.sticker","id":"mxc://matrix.axelchat.ru/CGLoWlTaqmQkAZVoCDAPsOCh","net.maunium.telegram.sticker":null},{"body":"😝","url":"mxc://matrix.axelchat.ru/OTapQggXXTtUEVknLwXFkTmr","info":{"w":512,"h":512,"size":3860056,"mimetype":"image/webp","thumbnail_url":"mxc://matrix.axelchat.ru/dWswyhiOprQKwZbczbXcEaQy","thumbnail_info":{"w":128,"h":128,"size":4250,"mimetype":"image/webp"}},"msgtype":"m.sticker","id":"mxc://matrix.axelchat.ru/OTapQggXXTtUEVknLwXFkTmr","net.maunium.telegram.sticker":null},{"body":"😡","url":"mxc://matrix.axelchat.ru/TdZIHAnIeJJqyOssMqxMWAvg","info":{"w":512,"h":512,"size":5179658,"mimetype":"image/webp","thumbnail_url":"mxc://matrix.axelchat.ru/MCGPwOXorfnGypnsTHJrlSWY","thumbnail_info":{"w":128,"h":128,"size":5512,"mimetype":"image/webp"}},"msgtype":"m.sticker","id":"mxc://matrix.axelchat.ru/TdZIHAnIeJJqyOssMqxMWAvg","net.maunium.telegram.sticker":null},{"body":"🤷‍♂","url":"mxc://matrix.axelchat.ru/ftJxLXduYurdpVvtmKPPFnBT","info":{"w":512,"h":512,"size":4965188,"mimetype":"image/webp","thumbnail_url":"mxc://matrix.axelchat.ru/BvjUYPwrngsABEbFTyWJKXFg","thumbnail_info":{"w":128,"h":128,"size":5178,"mimetype":"image/webp"}},"msgtype":"m.sticker","id":"mxc://matrix.axelchat.ru/ftJxLXduYurdpVvtmKPPFnBT","net.maunium.telegram.sticker":null},{"body":"🥳","url":"mxc://matrix.axelchat.ru/guFoRZCxRORIhtpSXsoJYvWz","info":{"w":512,"h":512,"size":5270342,"mimetype":"image/webp","thumbnail_url":"mxc://matrix.axelchat.ru/kneawdSuoEmcbSQNUTQvJJJn","thumbnail_info":{"w":128,"h":128,"size":6086,"mimetype":"image/webp"}},"msgtype":"m.sticker","id":"mxc://matrix.axelchat.ru/guFoRZCxRORIhtpSXsoJYvWz","net.maunium.telegram.sticker":null},{"body":"❤️","url":"mxc://matrix.axelchat.ru/VCiRcSfUcAmfauiufbABoBGe","info":{"w":512,"h":512,"size":7724300,"mimetype":"image/webp","thumbnail_url":"mxc://matrix.axelchat.ru/auzMVjtVAQhqRTvNkfTHwOeh","thumbnail_info":{"w":128,"h":128,"size":6248,"mimetype":"image/webp"}},"msgtype":"m.sticker","id":"mxc://matrix.axelchat.ru/VCiRcSfUcAmfauiufbABoBGe","net.maunium.telegram.sticker":null},{"body":"😇","url":"mxc://matrix.axelchat.ru/giuqlPhJYBdMgKZsVDNnVBeE","info":{"w":512,"h":512,"size":5366264,"mimetype":"image/webp","thumbnail_url":"mxc://matrix.axelchat.ru/lRgOkYVwiZrJjooTTftfYjvw","thumbnail_info":{"w":128,"h":128,"size":5094,"mimetype":"image/webp"}},"msgtype":"m.sticker","id":"mxc://matrix.axelchat.ru/giuqlPhJYBdMgKZsVDNnVBeE","net.maunium.telegram.sticker":null},{"body":"☺️","url":"mxc://matrix.axelchat.ru/uVZZOokKqfBkGYwZDoPUyHeh","info":{"w":512,"h":512,"size":6587370,"mimetype":"image/webp","thumbnail_url":"mxc://matrix.axelchat.ru/dPlPCIxRPpiWBBOtjQIRFrLP","thumbnail_info":{"w":128,"h":128,"size":5810,"mimetype":"image/webp"}},"msgtype":"m.sticker","id":"mxc://matrix.axelchat.ru/uVZZOokKqfBkGYwZDoPUyHeh","net.maunium.telegram.sticker":null},{"body":"☺️","url":"mxc://matrix.axelchat.ru/GzZDlCNfccFcXaOSxvEKSiom","info":{"w":512,"h":512,"size":4605760,"mimetype":"image/webp","thumbnail_url":"mxc://matrix.axelchat.ru/zSJVozxQDWnSgEztwdRVWcgC","thumbnail_info":{"w":128,"h":128,"size":4904,"mimetype":"image/webp"}},"msgtype":"m.sticker","id":"mxc://matrix.axelchat.ru/GzZDlCNfccFcXaOSxvEKSiom","net.maunium.telegram.sticker":null}]}